ezqt_widgets/__init__.py
ezqt_widgets/button/__init__.py
ezqt_widgets/button/date_button.py
ezqt_widgets/button/icon_button.py
ezqt_widgets/button/loader_button.py
ezqt_widgets/cli/__init__.py
ezqt_widgets/cli/main.py
ezqt_widgets/cli/runner.py
ezqt_widgets/input/__init__.py
ezqt_widgets/input/auto_complete_input.py
ezqt_widgets/input/password_input.py
ezqt_widgets/input/search_input.py
ezqt_widgets/input/tab_replace_textedit.py
ezqt_widgets/label/__init__.py
ezqt_widgets/label/clickable_tag_label.py
ezqt_widgets/label/framed_label.py
ezqt_widgets/label/hover_label.py
ezqt_widgets/label/indicator_label.py
ezqt_widgets/misc/__init__.py
ezqt_widgets/misc/circular_timer.py
ezqt_widgets/misc/draggable_list.py
ezqt_widgets/misc/option_selector.py
ezqt_widgets/misc/toggle_icon.py
ezqt_widgets/misc/toggle_switch.py
ezqt_widgets-2.3.2.dist-info/licenses/LICENSE
ezqt_widgets-2.3.2.dist-info/METADATA
ezqt_widgets-2.3.2.dist-info/WHEEL
ezqt_widgets-2.3.2.dist-info/top_level.txt
ezqt_widgets-2.3.2.dist-info/RECORD
