Metadata-Version: 2.4
Name: EzQt-Widgets
Version: 2.3.2
Summary: Une collection de widgets Qt personnalisés et réutilisables pour PySide6. Fournit des composants graphiques avancés, réutilisables et stylés pour faciliter le développement d'interfaces modernes et ergonomiques.
Author: Neuraaak
Maintainer: Neuraaak
License: MIT
Project-URL: Homepage, https://github.com/neuraaak/ezqt_widgets
Project-URL: Repository, https://github.com/neuraaak/ezqt_widgets
Project-URL: PyPI, https://pypi.org/project/ezqt_widgets/
Keywords: qt,pyside6,widgets,gui,interface,components,ui,desktop
Classifier: Programming Language :: Python :: 3
Classifier: Programming Language :: Python :: 3.10
Classifier: Programming Language :: Python :: 3.11
Classifier: Programming Language :: Python :: 3.12
Classifier: Programming Language :: Python :: 3.13
Classifier: License :: OSI Approved :: MIT License
Classifier: Operating System :: OS Independent
Classifier: Development Status :: 5 - Production/Stable
Classifier: Intended Audience :: Developers
Classifier: Topic :: Software Development :: Libraries :: Python Modules
Classifier: Topic :: Software Development :: User Interfaces
Classifier: Topic :: Desktop Environment
Classifier: Topic :: Software Development :: Widget Sets
Requires-Python: >=3.10
License-File: LICENSE
Requires-Dist: PySide6<7.0.0,>=6.7.3
Requires-Dist: requests>=2.32.4
Requires-Dist: click>=8.2.1
Requires-Dist: PyYAML>=6.0
Requires-Dist: typing_extensions>=4.0.0
Provides-Extra: dev
Requires-Dist: black>=23.0.0; extra == "dev"
Requires-Dist: isort>=5.12.0; extra == "dev"
Requires-Dist: ruff>=0.1.0; extra == "dev"
Requires-Dist: ty>=0.0.13; extra == "dev"
Requires-Dist: pyright>=1.1.0; extra == "dev"
Requires-Dist: pre-commit>=3.0.0; extra == "dev"
Requires-Dist: bandit>=1.7.0; extra == "dev"
Requires-Dist: pytest>=7.0.0; extra == "dev"
Requires-Dist: pytest-cov>=4.0.0; extra == "dev"
Requires-Dist: pytest-mock>=3.10.0; extra == "dev"
Requires-Dist: pytest-xdist>=3.0.0; extra == "dev"
Requires-Dist: build>=1.0.0; extra == "dev"
Requires-Dist: twine>=4.0.0; extra == "dev"
Provides-Extra: test
Requires-Dist: pytest>=7.0.0; extra == "test"
Requires-Dist: pytest-cov>=4.0.0; extra == "test"
Requires-Dist: pytest-mock>=3.10.0; extra == "test"
Requires-Dist: pytest-xdist>=3.0.0; extra == "test"
Dynamic: license-file
